pdfquad/__init__.py
pdfquad/__main__.py
pdfquad/jpegquality.py
pdfquad/pdfquad.py
pdfquad/properties.py
pdfquad/schematron.py
pdfquad/shared.py
pdfquad/profiles/dbnl-fulltext.xml
pdfquad/profiles/kb-brussel.xml
pdfquad/profiles/kbr.xml
pdfquad/schemas/pdf-dbnl-50.sch
pdfquad/schemas/pdf-dbnl-85.sch
pdfquad/schemas/pdf-kb-brussel-50.sch
pdfquad/schemas/pdf-kb-brussel-85.sch
pdfquad/schemas/pdf-kbr-50.sch
pdfquad/schemas/pdf-kbr-85.sch
pdfquad-0.3.0.dist-info/LICENSE
pdfquad-0.3.0.dist-info/METADATA
pdfquad-0.3.0.dist-info/WHEEL
pdfquad-0.3.0.dist-info/entry_points.txt
pdfquad-0.3.0.dist-info/top_level.txt
pdfquad-0.3.0.dist-info/RECORD
