Metadata-Version: 2.1
Name: pdfquad
Version: 0.3.0
Summary: PDF QUality Assessment for Digitisation batches
Home-page: https://github.com/KBNLresearch/pdfquad
Author: Johan van der Knijff
Author-email: johan.vanderknijff@kb.nl
Maintainer: Johan van der Knijff
Maintainer-email: johan.vanderknijff@kb.nl
License: Apache License (https://www.apache.org/licenses/LICENSE-2.0)
Download-URL: https://github.com/KBNLresearch/pdfquad/archive/0.3.0.tar.gz
Platform: POSIX
Platform: Windows
Classifier: Environment :: Console
Classifier: Programming Language :: Python :: 3
Requires-Python: >=3.8, <4
Requires-Dist: lxml
Requires-Dist: pillow (>=9.0.0)
Requires-Dist: pymupdf (>=1.24.3)
Requires-Dist: setuptools
